predylogic/__init__.py
predylogic/_version.py
predylogic/py.typed
predylogic/types.py
predylogic/predicate/__init__.py
predylogic/predicate/errs.py
predylogic/predicate/predicate.py
predylogic/register/__init__.py
predylogic/register/errs.py
predylogic/register/registry.py
predylogic/trace/__init__.py
predylogic/trace/trace.py
predylogic-0.0.1.dist-info/METADATA
predylogic-0.0.1.dist-info/WHEEL
predylogic-0.0.1.dist-info/RECORD
