Metadata-Version: 2.4
Name: predylogic
Version: 0.0.1
Summary: An embedded, composable schema-driven predicate logic engine.
Project-URL: Documentation, https://Nagato-Yuzuru.github.io/predylogic/
Project-URL: Homepage, https://Nagato-Yuzuru.github.io/predylogic/
Project-URL: Repository, https://github.com/Nagato-Yuzuru/predylogic
Author-email: Nagato Yuzuru <x4.nagato.yuzuru@gmail.com>
Keywords: configuration,policy-engine,predicate-logic,rule-engine,schema-driven
Classifier: Development Status :: 3 - Alpha
Classifier: Intended Audience :: Developers
Classifier: Operating System :: OS Independent
Classifier: Programming Language :: Python
Classifier: Programming Language :: Python :: 3
Classifier: Programming Language :: Python :: 3.10
Classifier: Programming Language :: Python :: 3.11
Classifier: Programming Language :: Python :: 3.12
Classifier: Programming Language :: Python :: 3.13
Classifier: Programming Language :: Python :: 3.14
Classifier: Topic :: Software Development :: Libraries
Classifier: Topic :: Software Development :: Libraries :: Python Modules
Classifier: Typing :: Typed
Requires-Python: <4.0,>=3.10
Requires-Dist: typing-extensions>=4.15.0
